asprin/__init__.py
asprin/asprin.py
asprin/asprin_lib.lp
asprin/examples/cp_acyclic.lp
asprin/examples/cp_general.lp
asprin/examples/cp_tree.lp
asprin/examples/example1.lp
asprin/examples/example2.lp
asprin/examples/example3.lp
asprin/src/__init__.py
asprin/src/main/__init__.py
asprin/src/main/clingo_help.py
asprin/src/main/main.py
asprin/src/program_parser/__init__.py
asprin/src/program_parser/basic.py
asprin/src/program_parser/preference.py
asprin/src/program_parser/program_parser.py
asprin/src/program_parser/transitive_closure.py
asprin/src/program_parser/visitor.py
asprin/src/solver/__init__.py
asprin/src/solver/controller.py
asprin/src/solver/solver.py
asprin/src/solver/metasp/__init__.py
asprin/src/solver/metasp/metasp.py
asprin/src/solver/metasp/metasp_programs.py
asprin/src/solver/metasp/reify.py
asprin/src/spec_parser/__init__.py
asprin/src/spec_parser/ast.py
asprin/src/spec_parser/parsetab.py
asprin/src/spec_parser/spec_lexer.py
asprin/src/spec_parser/spec_parser.py
asprin/src/spec_parser/ply/__init__.py
asprin/src/spec_parser/ply/lex.py
asprin/src/spec_parser/ply/yacc.py
asprin/src/tests/__init__.py
asprin/src/tests/tester.py
asprin/src/tests/utils.py
asprin/src/tests/asprin_lib/test001.lp
asprin/src/tests/asprin_lib/test002.lp
asprin/src/tests/asprin_lib/test003.lp
asprin/src/tests/asprin_lib/test004.lp
asprin/src/tests/asprin_lib/test005.lp
asprin/src/tests/asprin_lib/test006.lp
asprin/src/tests/asprin_lib/test007.lp
asprin/src/tests/asprin_lib/test008.lp
asprin/src/tests/asprin_lib/test009.lp
asprin/src/tests/asprin_lib/test010.lp
asprin/src/tests/asprin_lib/test011.lp
asprin/src/tests/asprin_lib/test012.lp
asprin/src/tests/asprin_lib/test013.lp
asprin/src/tests/asprin_lib/test014.lp
asprin/src/tests/asprin_lib/test015.lp
asprin/src/tests/asprin_lib/test016.lp
asprin/src/tests/asprin_lib/test017.lp
asprin/src/tests/asprin_lib/test018.lp
asprin/src/tests/asprin_lib/test019.lp
asprin-3.1.0.dist-info/METADATA
asprin-3.1.0.dist-info/RECORD
asprin-3.1.0.dist-info/WHEEL
asprin-3.1.0.dist-info/entry_points.txt
asprin-3.1.0.dist-info/top_level.txt
