Metadata-Version: 2.1
Name: asprin
Version: 3.1.0
Summary: Qualitative and quantitative optimization in answer set programming
Home-page: https://github.com/potassco/asprin
Author: Javier Romero
Author-email: javier@cs.uni-potsdam.de
License: MIT
Keywords: logic answer set programming preference optimization
Platform: UNKNOWN
Classifier: Development Status :: 3 - Alpha
Classifier: Environment :: Console
Classifier: Intended Audience :: Science/Research
Classifier: Topic :: Software Development :: Build Tools
Classifier: License :: OSI Approved :: MIT License
Classifier: Operating System :: OS Independent
Classifier: Natural Language :: English
Classifier: Programming Language :: Python :: 2.7
Classifier: Programming Language :: Python :: 3.5
Classifier: Topic :: Scientific/Engineering :: Artificial Intelligence
